[{"id": 1, "title": "Звук и  ярость", "author": "У.Фолкнер", "year": 2015, "status": "в наличии"}, {"id": 2, "title": "Колыбель для кошки", "author": "К. Воннегут", "year": 2019, "status": "выдана"}, {"id": 3, "title": "Портрет Дориана Грея", "author": "Оскар Уайлд", "year": 1888, "status": "удалена"}, {"id": 4, "title": "Мастер и Маргарита", "author": "М.Булгаков", "year": 1888, "status": "в наличии"}, {"id": 5, "title": "", "author": "", "year": 1990, "status": "удалена"}, {"id": 6, "title": "Убить пересмешника", "author": "Ли Харпер", "year": 1888, "status": "в наличии"}, {"id": 7, "title": "Замок на песке", "author": "Мердок Айрис", "year": 1988, "status": "удалена"}, {"id": 8, "title": "Капитанская дочка", "author": "А. Пушкин", "year": 1988, "status": "выдана"}, {"id": 9, "title": "1984", "author": "Д. Оруэлл", "year": 1988, "status": "в наличии"}, {"id": 10, "title": "Послемрак", "author": "Х.Мураками", "year": 1999, "status": "удалена"}, {"id": 11, "title": "Test book", "author": "Test author", "year": 1888, "status": "в наличии"}]